{"data_mtime":1738671011,"dep_lines":[67,48,63,64,66,41,46,60,61,70,1,1,1,1,1,1,1,1,1,1,1,1,1,1,44],"dep_prios":[5,5,5,5,5,5,10,10,5,10,5,30,30,30,30,30,30,30,30,30,30,30,30,30,10],"dependencies":["urllib3.util.url","urllib3.exceptions","urllib3.connection","urllib3.connectionpool","urllib3.poolmanager","__future__","warnings","typing","socket","ssl","builtins","_frozen_importlib","_ssl","_warnings","abc","enum","http","http.client","types","urllib3._base_connection","urllib3._request_methods","urllib3.util","urllib3.util.retry","urllib3.util.timeout"],"hash":"8f6ebe4990d32760297208d75d5b4978892db4e5","id":"urllib3.contrib.socks","ignore_all":true,"interface_hash":"7e26812ca894a920a91c5226c4411177f95a0176","mtime":1735573547,"options":{"allow_redefinition":false,"allow_untyped_globals":false,"always_false":[],"always_true":[],"bazel":false,"check_untyped_defs":true,"disable_bytearray_promotion":false,"disable_error_code":[],"disable_memoryview_promotion":false,"disabled_error_codes":[],"disallow_any_decorated":false,"disallow_any_explicit":false,"disallow_any_expr":false,"disallow_any_generics":true,"disallow_any_unimported":false,"disallow_incomplete_defs":true,"disallow_subclassing_any":true,"disallow_untyped_calls":true,"disallow_untyped_decorators":true,"disallow_untyped_defs":true,"enable_error_code":[],"enabled_error_codes":[],"extra_checks":true,"follow_imports":"normal","follow_imports_for_stubs":false,"follow_untyped_imports":false,"ignore_errors":false,"ignore_missing_imports":true,"implicit_optional":false,"implicit_reexport":false,"local_partial_types":false,"mypyc":false,"old_type_inference":false,"platform":"linux","plugins":[],"strict_concatenate":false,"strict_equality":true,"strict_optional":true,"warn_no_return":true,"warn_return_any":true,"warn_unreachable":false,"warn_unused_ignores":true},"path":"/home/sbrunner/.pyenv/versions/3.11.9/lib/python3.11/site-packages/urllib3/contrib/socks.py","plugin_data":null,"size":7549,"suppressed":["socks"],"version_id":"1.14.1"}