{"data_mtime":1738667297,"dep_lines":[9,1,3,4,5,6,7,1,1,1,1],"dep_prios":[5,5,10,10,10,10,5,5,30,30,30],"dependencies":["urllib3.fields","__future__","binascii","codecs","os","typing","io","builtins","_codecs","_frozen_importlib","abc"],"hash":"963087efaa05111fddcd35b6ec79a3ef0f489d46","id":"urllib3.filepost","ignore_all":true,"interface_hash":"6132b395012d30f2d14fd66b7ab32bc19f07f90b","mtime":1735573547,"options":{"allow_redefinition":false,"allow_untyped_globals":false,"always_false":[],"always_true":[],"bazel":false,"check_untyped_defs":true,"disable_bytearray_promotion":false,"disable_error_code":[],"disable_memoryview_promotion":false,"disabled_error_codes":[],"disallow_any_decorated":false,"disallow_any_explicit":false,"disallow_any_expr":false,"disallow_any_generics":true,"disallow_any_unimported":false,"disallow_incomplete_defs":true,"disallow_subclassing_any":true,"disallow_untyped_calls":true,"disallow_untyped_decorators":true,"disallow_untyped_defs":true,"enable_error_code":[],"enabled_error_codes":[],"extra_checks":true,"follow_imports":"normal","follow_imports_for_stubs":false,"follow_untyped_imports":false,"ignore_errors":false,"ignore_missing_imports":true,"implicit_optional":false,"implicit_reexport":false,"local_partial_types":false,"mypyc":false,"old_type_inference":false,"platform":"linux","plugins":[],"strict_concatenate":false,"strict_equality":true,"strict_optional":true,"warn_no_return":true,"warn_return_any":true,"warn_unreachable":false,"warn_unused_ignores":true},"path":"/home/sbrunner/.pyenv/versions/3.11.9/lib/python3.11/site-packages/urllib3/filepost.py","plugin_data":null,"size":2388,"suppressed":[],"version_id":"1.14.1"}